geollama/.api_token/.token
geollama/__init__.py
geollama/calc_by_slice.py
geollama/config.py
geollama/evaluate.py
geollama/io.py
geollama/main.py
geollama/objects.py
geollama/prog_bar.py
geollama/report.py
geollama/templates/__init__.py
geollama/templates/report_template.ipynb
geollama-1.0.1.dist-info/LICENSE
geollama-1.0.1.dist-info/METADATA
geollama-1.0.1.dist-info/WHEEL
geollama-1.0.1.dist-info/entry_points.txt
geollama-1.0.1.dist-info/RECORD
