Metadata-Version: 2.3
Name: GeoLlama
Version: 1.0.1
Summary: A Python package for estimating sample thickness in cryo electron tomograms
License: Apache License V.2
Author: Neville B.-y. Yee
Requires-Python: >=3.9
Classifier: License :: Other/Proprietary License
Classifier: Programming Language :: Python :: 3
Classifier: Programming Language :: Python :: 3.9
Classifier: Programming Language :: Python :: 3.10
Classifier: Programming Language :: Python :: 3.11
Classifier: Programming Language :: Python :: 3.12
Classifier: Programming Language :: Python :: 3.13
Requires-Dist: icecream
Requires-Dist: ipykernel
Requires-Dist: ipython
Requires-Dist: matplotlib
Requires-Dist: mrcfile
Requires-Dist: nbconvert
Requires-Dist: numpy
Requires-Dist: opencv-python
Requires-Dist: pandas
Requires-Dist: papermill
Requires-Dist: plotly
Requires-Dist: pyinstrument
Requires-Dist: pytest
Requires-Dist: rich
Requires-Dist: ruamel-yaml
Requires-Dist: scikit-image
Requires-Dist: scikit-learn
Requires-Dist: scipy
Requires-Dist: seaborn
Requires-Dist: starfile
Requires-Dist: tabulate
Requires-Dist: typer
Requires-Dist: typing-extensions
Requires-Dist: umap-learn
